PyGPTs/__init__.py
PyGPTs/Gemini/__init__.py
PyGPTs/Gemini/data.py
PyGPTs/Gemini/errors.py
PyGPTs/Gemini/functions.py
PyGPTs/Gemini/types.py
PyGPTs/HuggingFace/Configurations.py
PyGPTs/HuggingFace/GenerationConfig.py
PyGPTs/HuggingFace/Models.py
PyGPTs/HuggingFace/Pipelines.py
PyGPTs/HuggingFace/Tokenizers.py
PyGPTs/HuggingFace/Transformers.py
PyGPTs/HuggingFace/__init__.py
PyGPTs/HuggingFace/base_objects.py
PyGPTs/HuggingFace/flags.py
PyGPTs-2.0.0.dist-info/METADATA
PyGPTs-2.0.0.dist-info/WHEEL
PyGPTs-2.0.0.dist-info/top_level.txt
PyGPTs-2.0.0.dist-info/RECORD
