Metadata-Version: 2.2
Name: PyGPTs
Version: 2.0.0
Summary: PyGPTs simplifies interacting with AI models like Hugging Face Transformers and Google Gemini. It streamlines model management, handles rate limits, and provides an easy-to-use API for text generation and chat sessions.
Author: oddshellnick
Author-email: oddshellnick.programming@gmail.com
Requires-Dist: setuptools
Requires-Dist: protobuf~=5.28.3
Requires-Dist: pytz~=2024.2
Requires-Dist: torch~=2.5.1
Requires-Dist: pyvartools~=1.3.10
Requires-Dist: transformers~=4.46.2
Requires-Dist: google-genai~=1.0.0
Requires-Dist: numpy~=2.1.3
Requires-Dist: parameterized~=0.9.0
Dynamic: author
Dynamic: author-email
Dynamic: description
Dynamic: description-content-type
Dynamic: requires-dist
Dynamic: summary
